safe_typing/__init__.py
safe_typing-0.2.3.dist-info/METADATA
safe_typing-0.2.3.dist-info/WHEEL
safe_typing-0.2.3.dist-info/top_level.txt
safe_typing-0.2.3.dist-info/RECORD
