Metadata-Version: 2.4
Name: safe-typing
Version: 0.2.3
Summary: safe-typing is a module that provides a safe way to access types within the typing/typing_extensions namespaces.
Home-page: https://github.com/fswair/safe-typing
Author: Mert Sirakaya
Maintainer: fswair
Maintainer-email: contact@tomris.dev
License: MIT
Classifier: Development Status :: 4 - Beta
Classifier: Intended Audience :: Developers
Classifier: License :: OSI Approved :: MIT License
Classifier: Programming Language :: Python :: 3.10
Classifier: Programming Language :: Python :: 3.11
Classifier: Programming Language :: Python :: 3.12
Classifier: Programming Language :: Python :: 3.13
Requires-Python: >=3.10
Dynamic: author
Dynamic: classifier
Dynamic: description
Dynamic: description-content-type
Dynamic: home-page
Dynamic: license
Dynamic: maintainer
Dynamic: maintainer-email
Dynamic: requires-python
Dynamic: summary
